terminal_typing_tutor/__init__.py
terminal_typing_tutor/__main__.py
terminal_typing_tutor/_version.py
terminal_typing_tutor/constants.py
terminal_typing_tutor/main.py
terminal_typing_tutor/qotd.py
terminal_typing_tutor/series/D/1/data.yaml
terminal_typing_tutor/series/D/2/data.yaml
terminal_typing_tutor/series/D/3/data.yaml
terminal_typing_tutor/series/D/lesson_count
terminal_typing_tutor/series/D/menu.json
terminal_typing_tutor/series/D/title
terminal_typing_tutor/series/M/1/data.yaml
terminal_typing_tutor/series/M/10/data.yaml
terminal_typing_tutor/series/M/11/data.yaml
terminal_typing_tutor/series/M/2/data.yaml
terminal_typing_tutor/series/M/3/data.yaml
terminal_typing_tutor/series/M/4/data.yaml
terminal_typing_tutor/series/M/5/data.yaml
terminal_typing_tutor/series/M/6/data.yaml
terminal_typing_tutor/series/M/7/data.yaml
terminal_typing_tutor/series/M/8/data.yaml
terminal_typing_tutor/series/M/9/data.yaml
terminal_typing_tutor/series/M/lesson_count
terminal_typing_tutor/series/M/m.typ
terminal_typing_tutor/series/M/menu.json
terminal_typing_tutor/series/M/title
terminal_typing_tutor/series/Q/1/data.yaml
terminal_typing_tutor/series/Q/2/data.yaml
terminal_typing_tutor/series/Q/3/data.yaml
terminal_typing_tutor/series/Q/4/data.yaml
terminal_typing_tutor/series/Q/5/data.yaml
terminal_typing_tutor/series/Q/lesson_count
terminal_typing_tutor/series/Q/menu.json
terminal_typing_tutor/series/Q/q.typ
terminal_typing_tutor/series/Q/title
terminal_typing_tutor/series/R/1/data.yaml
terminal_typing_tutor/series/R/10/data.yaml
terminal_typing_tutor/series/R/11/data.yaml
terminal_typing_tutor/series/R/12/data.yaml
terminal_typing_tutor/series/R/13/data.yaml
terminal_typing_tutor/series/R/14/data.yaml
terminal_typing_tutor/series/R/2/data.yaml
terminal_typing_tutor/series/R/3/data.yaml
terminal_typing_tutor/series/R/4/data.yaml
terminal_typing_tutor/series/R/5/data.yaml
terminal_typing_tutor/series/R/6/data.yaml
terminal_typing_tutor/series/R/7/data.yaml
terminal_typing_tutor-0.6.1.dist-info/LICENSE
terminal_typing_tutor-0.6.1.dist-info/METADATA
terminal_typing_tutor-0.6.1.dist-info/WHEEL
terminal_typing_tutor-0.6.1.dist-info/entry_points.txt
terminal_typing_tutor-0.6.1.dist-info/RECORD
