Metadata-Version: 2.1
Name: terminal-typing-tutor
Version: 0.6.1
Summary: Improve your touch-typing skills in the terminal, based on the GNU Typist program
Home-page: https://github.com/justinsgithub/terminal-typing-tutor
License: GPL-3.0-only
Author: Justin Angeles
Author-email: justinaawd@gmail.com
Requires-Python: >=3.8,<4.0
Classifier: License :: OSI Approved :: GNU General Public License v3 (GPLv3)
Classifier: Programming Language :: Python :: 3
Classifier: Programming Language :: Python :: 3.8
Classifier: Programming Language :: Python :: 3.9
Classifier: Programming Language :: Python :: 3.10
Classifier: Programming Language :: Python :: 3.11
Classifier: Programming Language :: Python :: 3.12
Requires-Dist: blessed (>=1.20.0,<2.0.0)
Requires-Dist: pyyaml (>=6.0,<7.0)
Requires-Dist: typer[all] (>=0.9.0,<0.10.0)
Requires-Dist: wikiquote (>=0.1.17,<0.2.0)
Project-URL: Documentation, https://github.com/justinsgithub/terminal-typing-tutor
Project-URL: Repository, https://github.com/justinsgithub/terminal-typing-tutor
